.gitignore
LICENSE
MANIFEST.in
README.md
setup.py
bernhard/__init__.py
bernhard/pb.py
bernhard_py3.egg-info/PKG-INFO
bernhard_py3.egg-info/SOURCES.txt
bernhard_py3.egg-info/dependency_links.txt
bernhard_py3.egg-info/not-zip-safe
bernhard_py3.egg-info/requires.txt
bernhard_py3.egg-info/top_level.txt